odoo8_addon_mrp_produce_uos-8.0.1.0.0.99.dev11-py2.7-nspkg.pth
odoo8_addon_mrp_produce_uos-8.0.1.0.0.99.dev11.dist-info/DESCRIPTION.rst
odoo8_addon_mrp_produce_uos-8.0.1.0.0.99.dev11.dist-info/METADATA
odoo8_addon_mrp_produce_uos-8.0.1.0.0.99.dev11.dist-info/RECORD
odoo8_addon_mrp_produce_uos-8.0.1.0.0.99.dev11.dist-info/WHEEL
odoo8_addon_mrp_produce_uos-8.0.1.0.0.99.dev11.dist-info/metadata.json
odoo8_addon_mrp_produce_uos-8.0.1.0.0.99.dev11.dist-info/namespace_packages.txt
odoo8_addon_mrp_produce_uos-8.0.1.0.0.99.dev11.dist-info/top_level.txt
odoo_addons/mrp_produce_uos/README.rst
odoo_addons/mrp_produce_uos/__init__.py
odoo_addons/mrp_produce_uos/__openerp__.py
odoo_addons/mrp_produce_uos/i18n/de.po
odoo_addons/mrp_produce_uos/i18n/es.po
odoo_addons/mrp_produce_uos/i18n/fr.po
odoo_addons/mrp_produce_uos/i18n/hr.po
odoo_addons/mrp_produce_uos/i18n/it.po
odoo_addons/mrp_produce_uos/i18n/mrp_produce_uos.pot
odoo_addons/mrp_produce_uos/i18n/sl.po
odoo_addons/mrp_produce_uos/static/description/icon.png
odoo_addons/mrp_produce_uos/tests/__init__.py
odoo_addons/mrp_produce_uos/tests/test_mrp_produce_uos.py
odoo_addons/mrp_produce_uos/wizard/__init__.py
odoo_addons/mrp_produce_uos/wizard/mrp_product_produce.py
odoo_addons/mrp_produce_uos/wizard/mrp_product_produce_view.xml
